[
  {
    "besttitle": " ุงูุถู 10 ุงูุฏุงู ูู ูู ูููุง 22 .. ุงูุฏุงู ูู ูุญู ุงูุฎูุงุงุงุงุงุงุงุงุงู ๐๐ฅ๐",
    "bestyoutube": "YiI0_I-kscE",
    "besttime": "25/09/2022"
  },

  {
    "besttitle": "ุชููุน ุตูุช ุงููุนุจุฉ ูุน ุงูููุชููุจุฑุฒ ๐ฎ๐คฃ",
    "bestyoutube": "YJ-zlHAoXSI",
    "besttime": "24/11/2021"
  },

  {
    "besttitle": "ูุนุจุฉ ูุงููุง ูุน ูุงููููุฒ 2 | ุงููุฑุงุฑ ุงูุญุงุณู ุนูุฏ ุจูุฏุฑูุชุง ..๐ต๏ธโโ๏ธ!!",
    "bestyoutube": "IAMju8iENkA",
    "besttime": "31/08/2021"
  },

    
  {
    "title": "ุฃููู ุชุญุฏู ูู ุฃุจูููู ๐๐ฅ! - VidCon Abu Dhabi",
    "youtube": "lxTTXr0ARNc",
    "time": "13/12/2021"
  },

  {
    "title": "ูุงููู ูููุฏ ูุน ุงููุงููููุฒ๐๐ฆ",
    "youtube": "gVSjop6MSbQ",
    "time": "25/12/2021"
  },

  {
    "title": "ุงููู ูุตู ุฌุจูู ูู ูุถููู ุงูุดูุฎ ูู ุงูุชูู ุชูู ๐๐",
    "youtube": "wqcTZSNFkhs",
    "time": "30/01/2022"
  }

]
